polaris/__init__.py
polaris/params.py
polaris/polaris.py
polaris/trials.py
polaris/examples/__init__.py
polaris/examples/parallel.py
polaris/examples/single.py
polaris/examples/utils.py
polaris/examples/chainer_mn_cifar10/__init__.py
polaris/examples/chainer_mn_cifar10/optimizer.py
polaris/examples/chainer_mn_cifar10/train.py
polaris/examples/chainer_mn_cifar10/models/__init__.py
polaris/examples/chainer_mn_cifar10/models/lenet5.py
polaris/examples/chainer_mn_cifar10/models/resnet50.py
polaris/optimizers/__init__.py
polaris/optimizers/bayesian_opt.py
polaris/optimizers/rand.py
polaris/optimizers/tpe.py
polaris/rabbitmq/__init__.py
polaris/rabbitmq/client.py
polaris/rabbitmq/config.py
polaris/rabbitmq/worker.py
polaris_py-0.7.3.data/scripts/polaris-worker
polaris_py-0.7.3.dist-info/METADATA
polaris_py-0.7.3.dist-info/RECORD
polaris_py-0.7.3.dist-info/WHEEL
polaris_py-0.7.3.dist-info/top_level.txt
