Metadata-Version: 2.1
Name: polaris-py
Version: 0.7.3
Summary: Polaris is a hyperparamter optimization library.
Home-page: UNKNOWN
Author: Shun Iwase, Linsho Kaku
Author-email: s@sh8.io, kaku.l.aa@rio.gsic.titech.ac.jp
License: MIT
Platform: Linux
Platform: OS-X
Classifier: Development Status :: 3 - Alpha
Classifier: Intended Audience :: Education
Classifier: Intended Audience :: Science/Research
Classifier: Intended Audience :: Developers
Classifier: Environment :: Console
Classifier: License :: OSI Approved :: MIT License
Classifier: Operating System :: MacOS :: MacOS X
Classifier: Operating System :: POSIX
Classifier: Operating System :: Unix
Classifier: Programming Language :: Python :: 3
Classifier: Programming Language :: Python :: 3.6
Requires-Dist: numpy
Requires-Dist: scikit-learn
Requires-Dist: scipy
Requires-Dist: pika (==0.12.0)
Requires-Dist: statsmodels
Requires-Dist: matplotlib
